sandrock_translator/__init__.py
sandrock_translator/main.py
sandrock_translator-1.1.0.dist-info/LICENSE.txt
sandrock_translator-1.1.0.dist-info/METADATA
sandrock_translator-1.1.0.dist-info/WHEEL
sandrock_translator-1.1.0.dist-info/entry_points.txt
sandrock_translator-1.1.0.dist-info/RECORD
