Metadata-Version: 2.1
Name: sandrock-translator
Version: 1.1.0
Summary: My Time At Sandrock translation parsing and machine translation tool
License: MIT
Author: sladkkr
Author-email: klimczakkarol@outlook.com
Requires-Python: >=3.11,<4.0
Classifier: License :: OSI Approved :: MIT License
Classifier: Programming Language :: Python :: 3
Classifier: Programming Language :: Python :: 3.11
Classifier: Programming Language :: Python :: 3.12
Requires-Dist: googletrans (>=3.1.0-alpha,<4.0.0)
Requires-Dist: progressbar (>=2.5,<3.0)
